valer.panic-1.0.1rc11-nspkg.pth
senaite/panic/__init__.py
senaite/panic/configure.zcml
senaite/panic/controlpanel.py
senaite/panic/interfaces.py
senaite/panic/setuphandlers.py
senaite/panic/utils.py
senaite/panic/adapters/__init__.py
senaite/panic/adapters/configure.zcml
senaite/panic/adapters/content.py
senaite/panic/adapters/listing.py
senaite/panic/browser/__init__.py
senaite/panic/browser/configure.zcml
senaite/panic/browser/viewlets.py
senaite/panic/browser/views.py
senaite/panic/browser/templates/panic_alert_email.pt
senaite/panic/browser/templates/panic_alert_viewlet.pt
senaite/panic/locales/senaite.panic.pot
senaite/panic/locales/ca/LC_MESSAGES/senaite.panic.po
senaite/panic/locales/cs/LC_MESSAGES/senaite.panic.po
senaite/panic/locales/de/LC_MESSAGES/senaite.panic.po
senaite/panic/locales/en/LC_MESSAGES/senaite.panic.po
senaite/panic/locales/es/LC_MESSAGES/senaite.panic.po
senaite/panic/profiles/default/browserlayer.xml
senaite/panic/profiles/default/controlpanel.xml
senaite/panic/profiles/default/metadata.xml
senaite/panic/profiles/default/registry.xml
senaite/panic/profiles/default/senaite.panic.install.txt
senaite/panic/profiles/uninstall/browserlayer.xml
senaite/panic/profiles/uninstall/metadata.xml
senaite/panic/profiles/uninstall/senaite.panic.uninstall.txt
senaite/panic/static/img/icon.png
senaite/panic/static/img/panic.png
senaite/panic/static/js/email_popup.js
senaite/panic/tests/__init__.py
senaite/panic/tests/base.py
senaite/panic/tests/test_doctests.py
senaite/panic/tests/test_setup.py
senaite/panic/tests/doctests/README
valer.panic-1.0.1rc11.dist-info/DESCRIPTION.rst
valer.panic-1.0.1rc11.dist-info/METADATA
valer.panic-1.0.1rc11.dist-info/RECORD
valer.panic-1.0.1rc11.dist-info/WHEEL
valer.panic-1.0.1rc11.dist-info/entry_points.txt
valer.panic-1.0.1rc11.dist-info/metadata.json
valer.panic-1.0.1rc11.dist-info/namespace_packages.txt
valer.panic-1.0.1rc11.dist-info/top_level.txt
